{
    "description": "",
    "tags": [],
    "size": {
        "height": 256,
        "width": 1600
    },
    "objects": [
        {
            "id": 29482366,
            "classId": 50139,
            "description": "",
            "geometryType": "bitmap",
            "labelerLogin": "gr@datasetninja.com",
            "createdAt": "2023-09-07T14:13:48.625Z",
            "updatedAt": "2023-09-07T14:13:48.625Z",
            "tags": [],
            "classTitle": "defect_3",
            "bitmap": {
                "data": "eJzrDPBz5+WS4mJgYOD19HAJAtISDAyMDIzMQNZkb5WfQIotwCfEFUj///9/6c35d4EsxpIgv2AGh2c30oAcDU8Xx5CKOckT/v+f32j3Q/7ojboLD+wPs13//9+w50O7Y+P/YFb7BexsDO+aU14/fLncDaiHwdPVz2WdU0ITAEfRLQI=",
                "origin": [
                    613,
                    0
                ]
            }
        }
    ]
}