{
    "description": "",
    "tags": [],
    "size": {
        "height": 256,
        "width": 1600
    },
    "objects": [
        {
            "id": 29482754,
            "classId": 50139,
            "description": "",
            "geometryType": "bitmap",
            "labelerLogin": "gr@datasetninja.com",
            "createdAt": "2023-09-07T14:14:35.116Z",
            "updatedAt": "2023-09-07T14:14:35.116Z",
            "tags": [],
            "classTitle": "defect_3",
            "bitmap": {
                "data": "eJzrDPBz5+WS4mJgYOD19HAJAtKyDAyMDIzMQFZp0vu9QIotwCfEFUj///9/6c35d4EsxpIgv2AGh2c30oAcVU8Xx5CKOckr/v/f35hYIMzuxtnVwd4884f9j07+xSyuR/odfRgYpkpM0DvMwyUE1MDg6ernss4poQkAMeklbw==",
                "origin": [
                    810,
                    0
                ]
            }
        }
    ]
}