{
    "description": "",
    "tags": [],
    "size": {
        "height": 256,
        "width": 1600
    },
    "objects": [
        {
            "id": 29485610,
            "classId": 50139,
            "description": "",
            "geometryType": "bitmap",
            "labelerLogin": "gr@datasetninja.com",
            "createdAt": "2023-09-07T14:19:43.358Z",
            "updatedAt": "2023-09-07T14:19:43.358Z",
            "tags": [],
            "classTitle": "defect_3",
            "bitmap": {
                "data": "eJzrDPBz5+WS4mJgYOD19HAJAtJCQHyLkRlITtzdcBZIsQX4hLgC6f///y+9Of8ukMVYEuQXzODw7EYakKPo6eIYUjEnOeHH8QMf6jc8/L9Ywj4vYYX80YoPjQdb/xswMLwM22X6QWnRRqBiBk9XP5d1TglNAHd3KjQ=",
                "origin": [
                    525,
                    38
                ]
            }
        }
    ]
}