{
    "description": "",
    "tags": [],
    "size": {
        "height": 256,
        "width": 1600
    },
    "objects": [
        {
            "id": 29489203,
            "classId": 50139,
            "description": "",
            "geometryType": "bitmap",
            "labelerLogin": "gr@datasetninja.com",
            "createdAt": "2023-09-07T14:26:00.927Z",
            "updatedAt": "2023-09-07T14:26:00.927Z",
            "tags": [],
            "classTitle": "defect_3",
            "bitmap": {
                "data": "eJzrDPBz5+WS4mJgYOD19HAJAtJ8DAyMDIzMQNbO31fDgBRbgE+IK5D+////0pvz7wJZjCVBfsEMDs9upAE50p4ujiEVc5JXpCes+G/cxcbxN+GHfRcb30Z5BgZ+jW0Pnhr/FgUqY/B09XNZ55TQBAC60CJM",
                "origin": [
                    429,
                    0
                ]
            }
        },
        {
            "id": 29489202,
            "classId": 50139,
            "description": "",
            "geometryType": "bitmap",
            "labelerLogin": "gr@datasetninja.com",
            "createdAt": "2023-09-07T14:26:00.927Z",
            "updatedAt": "2023-09-07T14:26:00.927Z",
            "tags": [],
            "classTitle": "defect_3",
            "bitmap": {
                "data": "eJzrDPBz5+WS4mJgYOD19HAJAtJiQNzOyAwkNRys5wEptgCfEFcg/f///6U3598FshhLgvyCGRye3UgDciw8XRxDKuYk/zh+4MCH/+yMf9jt1x1v/z+x8//kvrcPdzQy1TT4/GHoeXrykLzGAfsNSXVNP/jr/jQzMhS8+Lbyj/L7U0AzGDxd/VzWOSU0AQCsszaj",
                "origin": [
                    468,
                    50
                ]
            }
        }
    ]
}