{
    "description": "",
    "tags": [],
    "size": {
        "height": 256,
        "width": 1600
    },
    "objects": [
        {
            "id": 29490346,
            "classId": 50139,
            "description": "",
            "geometryType": "bitmap",
            "labelerLogin": "gr@datasetninja.com",
            "createdAt": "2023-09-07T14:27:59.386Z",
            "updatedAt": "2023-09-07T14:27:59.386Z",
            "tags": [],
            "classTitle": "defect_3",
            "bitmap": {
                "data": "eJzrDPBz5+WS4mJgYOD19HAJAtKiQHyVkRlINhlqJgIptgCfEFcg/f///6U3598FshhLgvyCGRye3UgDcuQ9XRxDKuYk//j/n50590O7YpM8j2BNAsfDNsUmyYxGRg0ue9VCXpsaoFIGT1c/l3VOCU0A9qUhMQ==",
                "origin": [
                    385,
                    43
                ]
            }
        }
    ]
}