{
    "description": "",
    "tags": [],
    "size": {
        "height": 256,
        "width": 1600
    },
    "objects": [
        {
            "id": 29491920,
            "classId": 50138,
            "description": "",
            "geometryType": "bitmap",
            "labelerLogin": "gr@datasetninja.com",
            "createdAt": "2023-09-07T14:30:45.481Z",
            "updatedAt": "2023-09-07T14:30:45.481Z",
            "tags": [],
            "classTitle": "defect_2",
            "bitmap": {
                "data": "eJzrDPBz5+WS4mJgYOD19HAJAtL8QLyakRlINk8N+Qik2AJ8QlyB9P///5fenH8XyGIsCfILZnB4diMNyFHydHEMqZiT/OD/cQfFScsF/i7kuMlvsmo5y98FIn+X8/xNZmB4aPVoe/eRWH+gagZPVz+XdU4JTQA3/yh7",
                "origin": [
                    848,
                    0
                ]
            }
        }
    ]
}