{
    "description": "",
    "tags": [],
    "size": {
        "height": 256,
        "width": 1600
    },
    "objects": [
        {
            "id": 29492674,
            "classId": 50137,
            "description": "",
            "geometryType": "bitmap",
            "labelerLogin": "gr@datasetninja.com",
            "createdAt": "2023-09-07T14:31:47.225Z",
            "updatedAt": "2023-09-07T14:31:47.225Z",
            "tags": [],
            "classTitle": "defect_1",
            "bitmap": {
                "data": "eJzrDPBz5+WS4mJgYOD19HAJAtKSQKzNyAwkt0/d2Aak2AJ8QlyB9P///5fenH8XyGIsCfILZnB4diMNyJHydHEMqZiT/OP//3pm5rkcbFHCZxSaGg/OY2Q4LNXuxlvRqAtUxeDp6ueyzimhCQCFxyEL",
                "origin": [
                    183,
                    0
                ]
            }
        },
        {
            "id": 29492673,
            "classId": 50137,
            "description": "",
            "geometryType": "bitmap",
            "labelerLogin": "gr@datasetninja.com",
            "createdAt": "2023-09-07T14:31:47.225Z",
            "updatedAt": "2023-09-07T14:31:47.225Z",
            "tags": [],
            "classTitle": "defect_1",
            "bitmap": {
                "data": "eJzrDPBz5+WS4mJgYOD19HAJAtIyQKzAyAwkrau7GIEUW4BPiCuQ/v///9Kb8+8CWYwlQX7BDA7PbqQBOdqeLo4hFXOSExIS/h848OP/f/a2/yeOMN9x+QtkfhDireBk40jsn/qj3Y+BQb05XvPtfCsDoDYGT1c/l3VOCU0AYZcq/Q==",
                "origin": [
                    131,
                    24
                ]
            }
        },
        {
            "id": 29492672,
            "classId": 50137,
            "description": "",
            "geometryType": "bitmap",
            "labelerLogin": "gr@datasetninja.com",
            "createdAt": "2023-09-07T14:31:47.224Z",
            "updatedAt": "2023-09-07T14:31:47.224Z",
            "tags": [],
            "classTitle": "defect_1",
            "bitmap": {
                "data": "eJzrDPBz5+WS4mJgYOD19HAJAtKSQGzFyAwk6+UTdgAptgCfEFcg/f///6U3598FshhLgvyCGRye3UgDcnQ9XRxDKuYk/zjMwPL/f3On/QkXW8Mj9imH5ok4zWP4KN/8QL014bizSYLqjEIBBnWf5untasdPATUyeLr6uaxzSmgCAHMGKgQ=",
                "origin": [
                    117,
                    60
                ]
            }
        },
        {
            "id": 29492671,
            "classId": 50137,
            "description": "",
            "geometryType": "bitmap",
            "labelerLogin": "gr@datasetninja.com",
            "createdAt": "2023-09-07T14:31:47.224Z",
            "updatedAt": "2023-09-07T14:31:47.224Z",
            "tags": [],
            "classTitle": "defect_1",
            "bitmap": {
                "data": "eJzrDPBz5+WS4mJgYOD19HAJAtIyQGzMyAwk91n+MgFSbAE+Ia5A+v///0tvzr8LZDGWBPkFMzg8u5EG5Gh7ujiGVMxJTkj48b/R8Z+94RFmjkR/3UcMLSuWi11kUPwnrFDHsJfnCI8CD8Mjxzk/mO+xPgFqY/B09XNZ55TQBAAOpihP",
                "origin": [
                    164,
                    91
                ]
            }
        },
        {
            "id": 29492670,
            "classId": 50137,
            "description": "",
            "geometryType": "bitmap",
            "labelerLogin": "gr@datasetninja.com",
            "createdAt": "2023-09-07T14:31:47.223Z",
            "updatedAt": "2023-09-07T14:31:47.223Z",
            "tags": [],
            "classTitle": "defect_1",
            "bitmap": {
                "data": "eJzrDPBz5+WS4mJgYOD19HAJAtJKQKzNyAwk1dtOeAIptgCfEFcg/f///6U3598FshhLgvyCGRye3UgDctQ8XRxDKuYk//i/v7Gx8aG9gMwBz2vCnmYJim811Z5yTuKx8Kw7pMLg2r6gfFZXsA1QB4Onq5/LOqeEJgA4giZW",
                "origin": [
                    120,
                    213
                ]
            }
        }
    ]
}