{
    "description": "",
    "tags": [],
    "size": {
        "height": 256,
        "width": 1600
    },
    "objects": [
        {
            "id": 29497493,
            "classId": 50139,
            "description": "",
            "geometryType": "bitmap",
            "labelerLogin": "gr@datasetninja.com",
            "createdAt": "2023-09-07T14:41:08.517Z",
            "updatedAt": "2023-09-07T14:41:08.517Z",
            "tags": [],
            "classTitle": "defect_3",
            "bitmap": {
                "data": "eJzrDPBz5+WS4mJgYOD19HAJAtLSQPyfkRlIWp23bwJSbAE+Ia4gwf//l96cfxfIYiwJ8gtmcHh2Iw3IkfJ0cQypmJOckPDvf8PD//8Dk6ZIqLp1CrowMCiyXw+7I/sWyGJg8HT1c1nnlNAEAMEiIqw=",
                "origin": [
                    1319,
                    1
                ]
            }
        },
        {
            "id": 29497492,
            "classId": 50139,
            "description": "",
            "geometryType": "bitmap",
            "labelerLogin": "gr@datasetninja.com",
            "createdAt": "2023-09-07T14:41:08.517Z",
            "updatedAt": "2023-09-07T14:41:08.517Z",
            "tags": [],
            "classTitle": "defect_3",
            "bitmap": {
                "data": "eJzrDPBz5+WS4mJgYOD19HAJAtLSQPyfkRlIWp23bwJSbAE+Ia4gwf//l96cfxfIYiwJ8gtmcHh2Iw3IMfB0cQypmJP84/9/fubDDUJf///vTTn07///iT4n/v+/b2DECWTz9yQ0/f3/n53Zi4HhHO9sRe1vxi5AvQyern4u65wSmgB7WzJi",
                "origin": [
                    1391,
                    1
                ]
            }
        },
        {
            "id": 29497491,
            "classId": 50139,
            "description": "",
            "geometryType": "bitmap",
            "labelerLogin": "gr@datasetninja.com",
            "createdAt": "2023-09-07T14:41:08.516Z",
            "updatedAt": "2023-09-07T14:41:08.516Z",
            "tags": [],
            "classTitle": "defect_3",
            "bitmap": {
                "data": "eJzrDPBz5+WS4mJgYOD19HAJAtIKQPyfkRlIrrrj5guk2AJ8QlxBgv//L705/y6QxVgS5BfM4PDsRhqQo+Lp4hhSMSf5B1Devs3R50q/kIjgt+b5P+w9OH8GNik11RcIM6T+CyoqOFdUDVTP4Onq57LOKaEJAKMjKQw=",
                "origin": [
                    1432,
                    1
                ]
            }
        },
        {
            "id": 29497490,
            "classId": 50139,
            "description": "",
            "geometryType": "bitmap",
            "labelerLogin": "gr@datasetninja.com",
            "createdAt": "2023-09-07T14:41:08.514Z",
            "updatedAt": "2023-09-07T14:41:08.514Z",
            "tags": [],
            "classTitle": "defect_3",
            "bitmap": {
                "data": "eJzrDPBz5+WS4mJgYOD19HAJAtLiDAyMDIzMQFaSQ30JkGIL8AlxBdL///9fenP+XSCLsSTIL5jB4dmNNCBH0tPFMaRiTvKG///7E1Ue/xLs/9+T8ac+JZnhnlC3fNj/30ADGRg8Xf1c1jklNAEAbR8jpg==",
                "origin": [
                    1512,
                    0
                ]
            }
        }
    ]
}