{
    "description": "",
    "tags": [],
    "size": {
        "height": 256,
        "width": 1600
    },
    "objects": [
        {
            "id": 29498377,
            "classId": 50139,
            "description": "",
            "geometryType": "bitmap",
            "labelerLogin": "gr@datasetninja.com",
            "createdAt": "2023-09-07T14:42:30.037Z",
            "updatedAt": "2023-09-07T14:42:30.037Z",
            "tags": [],
            "classTitle": "defect_3",
            "bitmap": {
                "data": "eJzrDPBz5+WS4mJgYOD19HAJAtKWDAyMDIzMQJbxFR9xIMUW4BPiCqT///+/9Ob8u0AWY0mQXzCDw7MbaUCOjqeLY0jFnOQf/Iw8PIfnBdqfktDj+R14rCDxhLME7+IexfMP5FN5xNl+eyQyMBySb/59ubdxAVAfg6ern8s6p4QmALaJJ6s=",
                "origin": [
                    1340,
                    0
                ]
            }
        },
        {
            "id": 29498376,
            "classId": 50139,
            "description": "",
            "geometryType": "bitmap",
            "labelerLogin": "gr@datasetninja.com",
            "createdAt": "2023-09-07T14:42:30.035Z",
            "updatedAt": "2023-09-07T14:42:30.035Z",
            "tags": [],
            "classTitle": "defect_3",
            "bitmap": {
                "data": "eJzrDPBz5+WS4mJgYOD19HAJAtJaQGzByAwkNwr/6ABSbAE+Ia5A+v///0tvzr8LZDGWBPkFMzg8u5EG5Mh5ujiGVMxJXvH/fzMjx6v/zI6HBZY6PPnP7DyNCajtboLauh1u+9iAKhk8Xf1c1jklNAEAPCAkHw==",
                "origin": [
                    1457,
                    2
                ]
            }
        }
    ]
}